[
  {
    "userId": "Larsson@mail.com",
    "firstName": "Elin",
    "lastName": "Larsson",
    "answers": {
      "1": "role-student",
      "2": "exp-0-1",
      "4": [
        "goal-job"
      ],
      "5": [
        "type-senior",
        "type-recruiter"
      ],
      "6": [
        "industry-tech"
      ],
      "7": [
        "industry-tech"
      ],
      "8": [
        "skill-programming"
      ]
    },
    "createdAt": "2025-05-07T09:48:47.256Z",
    "index": 1
  },
  {
    "userId": "hej@ma.con",
    "firstName": "Sara",
    "lastName": "Movin",
    "answers": {
      "1": "role-recruiter",
      "2": "exp-3-5",
      "3": "yes",
      "4": [
        "goal-recruit"
      ],
      "5": [
        "type-student"
      ],
      "6": [
        "industry-tech"
      ],
      "7": [
        "industry-tech"
      ],
      "8": [
        "skill-programming"
      ]
    },
    "createdAt": "2025-05-07T09:49:36.530Z",
    "index": 2
  },
  {
    "userId": "hej@mil.lo",
    "firstName": "Sara",
    "lastName": "Andersson",
    "answers": {
      "1": "role-recruiter",
      "2": "exp-5-10",
      "3": "yes",
      "4": [
        "goal-job"
      ],
      "5": [
        "type-similar-role"
      ],
      "6": [
        "industry-finance"
      ],
      "7": [
        "industry-tourism"
      ],
      "8": [
        "skill-copywriting"
      ]
    },
    "createdAt": "2025-05-09T13:07:23.870Z",
    "index": 3
  },
  {
    "userId": "il@hu.se",
    "firstName": "Edvin",
    "lastName": "Gantelius",
    "answers": {},
    "createdAt": "2025-05-07T10:03:19.742Z",
    "index": 4
  },
  {
    "userId": "Sara.movin@gmail.com",
    "firstName": "Carolina",
    "lastName": "Cuevas",
    "answers": {
      "1": "role-graduate",
      "2": "exp-3-5",
      "3": "yes",
      "4": [
        "goal-recruit",
        "goal-none"
      ],
      "5": [
        "type-recruiter",
        "type-graduate"
      ],
      "6": [
        "industry-transport"
      ],
      "7": [
        "industry-transport"
      ],
      "8": [
        "skill-finance"
      ]
    },
    "createdAt": "2025-05-07T11:01:50.269Z",
    "index": 5
  },
  {
    "userId": "sara.hej@mail.so",
    "firstName": "Amanda",
    "lastName": "Thor",
    "answers": {
      "1": "role-graduate",
      "2": "exp-0-1",
      "4": [
        "goal-job",
        "goal-customers"
      ],
      "5": [
        "type-entrepreneur",
        "type-student"
      ],
      "6": [
        "industry-startups"
      ],
      "7": [
        "industry-health",
        "industry-startups"
      ],
      "8": [
        "skill-analysis",
        "skill-marketing"
      ]
    },
    "createdAt": "2025-05-07T12:50:59.894Z",
    "index": 6
  },
  {
    "userId": "sra@hej.com",
    "firstName": "Kajsa",
    "lastName": "Kajsson",
    "answers": {
      "1": "role-student",
      "2": "exp-1-3",
      "4": [
        "goal-recruit",
        "goal-job"
      ],
      "5": [
        "type-similar-role"
      ],
      "6": [
        "industry-tech"
      ],
      "7": [
        "industry-tech"
      ],
      "8": [
        "skill-programming"
      ]
    },
    "createdAt": "2025-05-13T09:34:48.368Z",
    "index": 7
  },
  {
    "userId": "nils.borg@demo.se",
    "firstName": "Nils",
    "lastName": "Babtist",
    "answers": {
      "1": "role-analyst",
      "2": "exp-5-10",
      "3": "no",
      "4": [
        "goal-contacts",
        "goal-inspiration"
      ],
      "5": [
        "type-student",
        "type-ceo"
      ],
      "6": [
        "industry-finance",
        "industry-public"
      ],
      "7": [
        "industry-tech",
        "industry-finance"
      ],
      "8": [
        "skill-analysis",
        "skill-strategy",
        "skill-communication"
      ],
      "9": [
        "skill-strategy",
        "skill-finance"
      ]
    },
    "createdAt": "2025-05-08T10:01:00.000Z",
    "index": 8
  },
  {
    "userId": "lena.ux@designlab.org",
    "firstName": "Lena",
    "lastName": "Karlsson",
    "answers": {
      "1": "role-developer",
      "2": "exp-1-3",
      "3": "yes",
      "4": [
        "goal-job"
      ],
      "5": [
        "type-similar-role"
      ],
      "6": [
        "industry-tech",
        "industry-creative"
      ],
      "7": [
        "industry-creative"
      ],
      "8": [
        "skill-design",
        "skill-development"
      ],
      "9": [
        "skill-design",
        "skill-communication"
      ]
    },
    "createdAt": "2025-05-09T13:24:41.174Z",
    "index": 9
  },
  {
    "userId": "amin.karim@buildcorp.com",
    "firstName": "Amin",
    "lastName": "Olsson",
    "answers": {
      "1": "role-engineer",
      "2": "exp-10plus",
      "3": "no",
      "4": [
        "goal-project",
        "goal-partners"
      ],
      "5": [
        "type-senior",
        "type-engineer"
      ],
      "6": [
        "industry-construction",
        "industry-energy"
      ],
      "7": [
        "industry-construction"
      ],
      "8": [
        "skill-project",
        "skill-leadership"
      ],
      "9": [
        "skill-development"
      ]
    },
    "createdAt": "2025-05-08T12:30:00.000Z",
    "index": 10
  },
  {
    "userId": "emelie.freelance@creative.nu",
    "firstName": "Emelie",
    "lastName": "Edstam",
    "answers": {
      "1": "role-entrepreneur",
      "2": "exp-3-5",
      "3": "yes",
      "4": [
        "goal-customers",
        "goal-contacts"
      ],
      "5": [
        "type-recruiter",
        "type-none"
      ],
      "6": [
        "industry-creative",
        "industry-trade"
      ],
      "7": [
        "industry-creative"
      ],
      "8": [
        "skill-copywriting",
        "skill-marketing",
        "skill-sales"
      ],
      "9": [
        "skill-marketing"
      ]
    },
    "createdAt": "2025-05-08T13:45:00.000Z",
    "index": 11
  },
  {
    "userId": "chris@nomail.com",
    "firstName": "Chris",
    "lastName": "Jenner",
    "answers": {
      "1": "role-admin",
      "2": "exp-0-1",
      "3": "no",
      "4": [
        "goal-none"
      ],
      "5": [
        "type-none"
      ],
      "6": [
        "industry-unemployed"
      ],
      "7": [
        "industry-unemployed"
      ],
      "8": [],
      "9": []
    },
    "createdAt": "2025-05-08T15:00:00.000Z",
    "index": 12
  },
  {
    "userId": "olivia.berg@edu.univ.se",
    "firstName": "Olivia",
    "lastName": "Diamanti",
    "answers": {
      "1": "role-student",
      "2": "exp-1-3",
      "3": "yes",
      "4": [
        "goal-inspiration",
        "goal-project"
      ],
      "5": [
        "type-senior",
        "type-graduate"
      ],
      "6": [
        "industry-education",
        "industry-hr"
      ],
      "7": [
        "industry-education",
        "industry-health"
      ],
      "8": [
        "skill-research",
        "skill-communication",
        "skill-project"
      ],
      "9": [
        "skill-communication",
        "skill-leadership"
      ]
    },
    "createdAt": "2025-05-08T16:00:00.000Z",
    "index": 13
  },
  {
    "userId": "tommy@logixtrans.se",
    "firstName": "Tommy",
    "lastName": "Loveless",
    "answers": {
      "1": "role-projectmanager",
      "2": "exp-5-10",
      "3": "no",
      "4": [
        "goal-partners",
        "goal-contacts"
      ],
      "5": [
        "type-similar-role",
        "type-ceo"
      ],
      "6": [
        "industry-transport",
        "industry-production"
      ],
      "7": [
        "industry-transport"
      ],
      "8": [
        "skill-leadership",
        "skill-strategy",
        "skill-development"
      ],
      "9": [
        "skill-project",
        "skill-analysis"
      ]
    },
    "createdAt": "2025-05-08T17:25:00.000Z",
    "index": 14
  },
  {
    "userId": "yasmin.fikri@startuphub.io",
    "firstName": "Yasmin",
    "lastName": "Fikri",
    "answers": {
      "1": "role-entrepreneur",
      "2": "exp-3-5",
      "3": "yes",
      "4": [
        "goal-job",
        "goal-customers",
        "goal-inspiration"
      ],
      "5": [
        "type-student",
        "type-entrepreneur"
      ],
      "6": [
        "industry-startups",
        "industry-creative"
      ],
      "7": [
        "industry-startups"
      ],
      "8": [
        "skill-marketing",
        "skill-copywriting",
        "skill-strategy"
      ],
      "9": [
        "skill-marketing",
        "skill-project"
      ]
    },
    "createdAt": "2025-05-12T09:37:10.282Z",
    "index": 15
  },
  {
    "userId": "axel.nilsson@publicgov.se",
    "firstName": "Axel",
    "lastName": "Freud",
    "answers": {
      "1": "role-economist",
      "2": "exp-10plus",
      "3": "no",
      "4": [
        "goal-project"
      ],
      "5": [
        "type-recruiter",
        "type-similar-role"
      ],
      "6": [
        "industry-public",
        "industry-finance"
      ],
      "7": [
        "industry-public"
      ],
      "8": [
        "skill-finance",
        "skill-strategy"
      ],
      "9": [
        "skill-finance"
      ]
    },
    "createdAt": "2025-05-13T13:46:49.688Z",
    "index": 16
  },
  {
    "userId": "elvira.juul@ecoenergy.se",
    "firstName": "Elvira",
    "lastName": "Södertörn",
    "answers": {
      "1": "role-consultant",
      "2": "exp-3-5",
      "3": "yes",
      "4": [
        "goal-job",
        "goal-inspiration"
      ],
      "5": [
        "type-senior",
        "type-none"
      ],
      "6": [
        "industry-energy",
        "industry-construction"
      ],
      "7": [
        "industry-energy"
      ],
      "8": [
        "skill-analysis",
        "skill-communication"
      ],
      "9": [
        "skill-research",
        "skill-development"
      ]
    },
    "createdAt": "2025-05-08T20:20:00.000Z",
    "index": 17
  },
  {
    "userId": "isak.rosen@futuretour.se",
    "firstName": "Isak",
    "lastName": "Isaksson",
    "answers": {
      "1": "role-sales",
      "2": "exp-1-3",
      "3": "no",
      "4": [
        "goal-contacts",
        "goal-customers"
      ],
      "5": [
        "type-student",
        "type-analyst"
      ],
      "6": [
        "industry-tourism",
        "industry-trade"
      ],
      "7": [
        "industry-tourism"
      ],
      "8": [
        "skill-sales",
        "skill-communication",
        "skill-marketing"
      ],
      "9": [
        "skill-sales",
        "skill-copywriting"
      ]
    },
    "createdAt": "2025-05-13T11:27:26.898Z",
    "index": 18
  },
  {
    "userId": "anna1@gmail.com",
    "firstName": "Anna",
    "lastName": "1",
    "answers": {
      "1": "role-student",
      "2": "exp-1-3",
      "3": "no",
      "4": [
        "goal-job",
        "goal-contacts"
      ],
      "5": [
        "type-senior",
        "type-recruiter"
      ],
      "6": [
        "industry-unemployed"
      ],
      "7": [
        "industry-tech"
      ],
      "8": [
        "skill-programming",
        "skill-design",
        "skill-marketing"
      ],
      "9": [
        "skill-programming",
        "skill-design"
      ]
    },
    "createdAt": "2025-05-13T10:03:21.933Z",
    "index": 18
  },
  {
    "userId": "anna2@gmail.com",
    "firstName": "Anna",
    "lastName": "2",
    "answers": {
      "8": [
        "skill-programming",
        "skill-project"
      ]
    },
    "createdAt": "2025-05-12T08:03:37.281Z",
    "index": 18
  },
  {
    "userId": "anna3@gmail.com",
    "firstName": "Anna",
    "lastName": "3",
    "answers": {
      "9": [
        "skill-programming",
        "skill-project"
      ]
    },
    "createdAt": "2025-05-12T08:03:54.641Z",
    "index": 18
  },
  {
    "userId": "anna4@gmail.com",
    "firstName": "Anna",
    "lastName": "4",
    "answers": {
      "1": "role-entrepreneur",
      "2": "exp-3-5",
      "3": "no",
      "4": [
        "goal-partners",
        "goal-project",
        "goal-contacts"
      ],
      "5": [
        "type-similar-role",
        "type-entrepreneur"
      ],
      "6": [
        "industry-startups"
      ],
      "7": [
        "industry-startups",
        "industry-tech",
        "industry-finance"
      ],
      "8": [
        "skill-project",
        "skill-leadership",
        "skill-analysis"
      ]
    },
    "createdAt": "2025-05-13T11:37:40.034Z",
    "index": 18
  },
  {
    "userId": "anna5@gmail.com",
    "firstName": "Anna",
    "lastName": "5",
    "answers": {
      "1": "role-recruiter",
      "2": "exp-1-3",
      "4": [
        "goal-recruit"
      ],
      "5": [
        "type-graduate",
        "type-student"
      ],
      "6": [
        "industry-tech"
      ],
      "7": [
        "industry-education",
        "industry-tech",
        "industry-finance"
      ],
      "8": [
        "skill-development"
      ],
      "9": [
        "skill-research",
        "skill-strategy"
      ]
    },
    "createdAt": "2025-05-13T13:09:05.402Z",
    "index": 18
  },
  {
    "userId": "anna6@gmail.com",
    "firstName": "Anna",
    "lastName": "6",
    "answers": {
      "1": "role-entrepreneur",
      "2": "exp-1-3",
      "4": [
        "goal-recruit",
        "goal-customers"
      ],
      "5": [
        "type-senior",
        "type-student"
      ],
      "6": [
        "industry-tourism"
      ],
      "7": [
        "industry-finance"
      ],
      "8": [
        "skill-design"
      ],
      "9": [
        "skill-finance"
      ]
    },
    "createdAt": "2025-05-14T08:11:38.715Z",
    "index": 18
  },
  {
    "userId": "anna7@gmail.com",
    "firstName": "Anna",
    "lastName": "7",
    "answers": {},
    "createdAt": "",
    "index": 18
  },
  {
    "userId": "anna8@gmail.com",
    "firstName": "Anna",
    "lastName": "8",
    "answers": {},
    "createdAt": "2025-05-12T14:33:28.998Z",
    "index": 18
  },
  {
    "userId": "anna9@gmail.com",
    "firstName": "Anna",
    "lastName": "9",
    "answers": {},
    "createdAt": "2025-05-12T15:44:35.536Z",
    "index": 18
  },
  {
    "userId": "anna10@gmail.com",
    "firstName": "Anna",
    "lastName": "10",
    "answers": {},
    "createdAt": "2025-05-14T13:28:49.247Z",
    "index": 18
  },
  {
    "userId": "emma@lindskog.se",
    "firstName": "Emma",
    "lastName": "GL",
    "answers": {
      "1": "role-ceo",
      "2": "exp-0-1",
      "4": [
        "goal-customers",
        "goal-inspiration",
        "goal-contacts"
      ],
      "5": [
        "type-similar-role",
        "type-graduate"
      ],
      "6": [
        "industry-tourism"
      ],
      "7": [
        "industry-tech",
        "industry-finance",
        "industry-startups"
      ],
      "8": [
        "skill-sales",
        "skill-leadership",
        "skill-project"
      ],
      "9": [
        "skill-sales",
        "skill-project",
        "skill-leadership"
      ]
    },
    "createdAt": "2025-05-13T13:11:52.836Z",
    "index": 18
  },
  {
    "userId": "tea.stjarne@gmail.com",
    "firstName": "Tea",
    "lastName": "Stjärne",
    "answers": {
      "9": [
        "skill-design",
        "skill-communication",
        "skill-programming"
      ]
    },
    "createdAt": "2025-05-13T13:15:48.388Z",
    "index": 18
  },
  {
    "userId": "henrik.swanberg@gmail.com",
    "firstName": "Henrik",
    "lastName": "Swanberg",
    "answers": {
      "1": "role-graduate",
      "2": "exp-1-3",
      "4": [
        "goal-job",
        "goal-customers",
        "goal-inspiration"
      ],
      "5": [
        "type-student",
        "type-recruiter",
        "type-senior"
      ],
      "6": [
        "industry-health"
      ],
      "7": [
        "industry-tech",
        "industry-hr",
        "industry-health"
      ],
      "8": [
        "skill-marketing",
        "skill-sales",
        "skill-leadership"
      ],
      "9": [
        "skill-leadership",
        "skill-project",
        "skill-strategy"
      ]
    },
    "createdAt": "2025-05-13T14:46:35.062Z",
    "index": 19
  },
  {
    "userId": "victor@ileklint.se",
    "firstName": "Victor",
    "lastName": "Ileklint",
    "answers": {
      "1": "role-consultant",
      "2": "exp-3-5",
      "3": "yes",
      "4": [
        "goal-customers",
        "goal-recruit",
        "goal-project"
      ],
      "5": [
        "type-student",
        "type-recruiter"
      ],
      "6": [
        "industry-startups"
      ],
      "7": [
        "industry-creative",
        "industry-finance"
      ],
      "8": [
        "skill-development",
        "skill-leadership",
        "skill-sales"
      ],
      "9": [
        "skill-analysis",
        "skill-leadership",
        "skill-strategy"
      ]
    },
    "createdAt": "2025-05-13T14:52:27.198Z",
    "index": 18
  }
]