[
  {
    "userId": "Elin@g.se",
    "firstName": "Elin",
    "lastName": "Elin",
    "answers": {
      "1": "Studenter",
      "2": "1-3 år",
      "4": [
        "Rekrytera"
      ],
      "5": [
        "Rekryterare"
      ],
      "6": [
        "Industri & produktion"
      ],
      "7": [
        "Transport & logistik"
      ],
      "8": [
        "Utveckling"
      ]
    },
    "createdAt": "2025-05-04T14:55:39.534Z",
    "index": 1
  },
  {
    "userId": "e@hej.gse",
    "firstName": "Elin",
    "lastName": "Elin",
    "answers": {
      "1": "Studenter",
      "2": "0-1 år",
      "4": [
        "Hitta samarbetspartners"
      ],
      "5": [
        "Entreprenörer/startups"
      ],
      "6": [
        "Startups & entreprenörskap"
      ],
      "7": [
        "Transport & logistik"
      ],
      "8": [
        "Kommunikation"
      ]
    },
    "createdAt": "2025-05-04T14:56:04.368Z",
    "index": 2
  }
]